{
  "current":{
    "logo":"disabled",
    "bg_color":"#ffffff",
    "bg_image":"disabled",
    "bg_repeat":"repeat",
    "bg_position":"0 0",
    "bg_attachment":"scroll",
    "typography":"'Lucida Grande', 'Lucida Sans Unicode', 'Lucida Sans', Lucida, Helvetica, Arial, sans-serif",
    "text_color":"#2c2f2f",
    "title_text_color":"#2c2f2f",
    "accent_text_color":"#999999",
    "link_color":"#a2d400",
    "link_hover":"#a2d400",
    "title_color":"#2c2f2f",
    "title_hover":"#a2d400",
    "header_text_color":"#2c2f2f",
    "header_link_color":"#a2d400",
    "header_link_hover":"#a2d400",
    "nav_link_color":"#2c2f2f",
    "nav_link_hover":"#2c2f2f",
    "overview_bg_color":"#f2f2f2",
    "overview_border_color":"#dedbdb",
    "overview_text_color":"#2c2f2f",
    "overview_title_text_color":"#2c2f2f",
    "overview_link_color":"#a2d400",
    "overview_link_hover":"#a2d400",
    "footer_text_color":"#2c2f2f",
    "footer_link_color":"#2c2f2f",
    "footer_link_hover":"#2c2f2f",
    "search_btn_text_color":"#ffffff",
    "search_btn_hover_color":"#ffffff",
    "search_btn_bg_color":"#9ebf2a",
    "search_btn_bg_hover":"#94b228",
    "phone":"555.555.555",
    "email":"info@fakedomain.com",
    "showcase":"The chic chair that's perfect for entertaining.",
    "related":"Take a look at these great accessories:",
    "notes":"Tell us about any special instructions:"
  }
}
